{
    "fields" : [
        {
            "component" : "FormInput",
            "props" : {
                "type" : "text",
                "id" : "name",
                "name" : "name",
                "defaultValue" : null,
                "placeholder": "Full Name",
				"autoComplete" : "name",
				"size" : "40",
				"display" : "horizontal",
				"required" : "required",
				"label" : "Name : ",
				"tooltip" : "Please enter your First and Last Name"
            }
        },
		{
            "component" : "FormInput",
            "props" : {
                "type" : "text",
                "id" : "street1",
                "name" : "street1",
                "defaultValue" : null,
                "placeholder": "Street Address",
				"autoComplete" : "street-address",
				"size" : "40",
				"display" : "horizontal",
				"required" : "required",
				"label" : "Street Address : ",
				"tooltip" : "Please enter your Street Address"
            }
        },
		{
            "component" : "FormInput",
            "props" : {
                "type" : "text",
                "id" : "city",
                "name" : "city",
                "defaultValue" : null,
                "placeholder": "City",
				"autoComplete" : "address-level2",
				"size" : "40",
				"display" : "horizontal",
				"required" : "required",
				"label" : "City : ",
				"tooltip" : "Please enter your City"
            }
        },
		{
            "component" : "FormSelect",
            "props" : {
                "id" : "state",
                "name" : "state",
				"size" : null,
				"defaultValue" : "",
                "placeholder": "State",
				"autoComplete" : "address-level1",
				"multiple" : null,
				"required" : "required",
				"display" : "horizontal",
				"label" : "State : ",
				"tooltip" : "Please select your State",
				"options" : [
					{ "value" : "", "text" : "" , "disabled" : "disabled"},
					{ "value" : "AL", "text" : "Alabama" },
					{ "value" : "AK", "text" : "Alaska" },
					{ "value" : "AZ", "text" : "Arizona" },
					{ "value" : "AR", "text" : "Arkansas" },
					{ "value" : "CA", "text" : "California" },
					{ "value" : "CO", "text" : "Colorado" },
					{ "value" : "CT", "text" : "Connecticut" },
					{ "value" : "DE", "text" : "Delaware" },
					{ "value" : "FL", "text" : "Florida" },
					{ "value" : "GA", "text" : "Georgia" },
					{ "value" : "HI", "text" : "Hawaii" },
					{ "value" : "ID", "text" : "Idaho" },
					{ "value" : "IL", "text" : "Illinois" },
					{ "value" : "IN", "text" : "Indiana" },
					{ "value" : "IA", "text" : "Iowa" },
					{ "value" : "KS", "text" : "Kansas" },
					{ "value" : "KY", "text" : "Kentucky" },
					{ "value" : "LA", "text" : "Louisiana" },
					{ "value" : "ME", "text" : "Maine" },
					{ "value" : "MD", "text" : "Maryland" },
					{ "value" : "MA", "text" : "Massachusetts" },
					{ "value" : "MI", "text" : "Michigan" },
					{ "value" : "MN", "text" : "Minnesota" },
					{ "value" : "MS", "text" : "Mississippi" },
					{ "value" : "MO", "text" : "Missouri" },
					{ "value" : "MT", "text" : "Montana" },
					{ "value" : "NB", "text" : "Nebraska" },
					{ "value" : "NV", "text" : "Nevada" },
					{ "value" : "NH", "text" : "New Hampshire" },
					{ "value" : "NJ", "text" : "New Jersey" },
					{ "value" : "NM", "text" : "New Mexico" },
					{ "value" : "NY", "text" : "New York" },
					{ "value" : "NC", "text" : "North Carolina" },
					{ "value" : "ND", "text" : "North Dakota" },
					{ "value" : "OH", "text" : "Ohio" },
					{ "value" : "OK", "text" : "Oklahoma" },
					{ "value" : "OR", "text" : "Oregon" },
					{ "value" : "PA", "text" : "Pennsylvania" },
					{ "value" : "RI", "text" : "Rhode Island" },
					{ "value" : "SC", "text" : "South Carolina" },
					{ "value" : "SD", "text" : "South Dakota" },
					{ "value" : "TN", "text" : "Tennessee" },
					{ "value" : "TX", "text" : "Texas" },
					{ "value" : "UT", "text" : "Utah" },
					{ "value" : "VT", "text" : "Vermont" },
					{ "value" : "VA", "text" : "Virginia" },
					{ "value" : "WA", "text" : "Washington" },
					{ "value" : "WV", "text" : "West Virginia" },
					{ "value" : "WI", "text" : "Wisconsin" },
					{ "value" : "WY", "text" : "Wyoming" }
				]
            }
        },
		{
            "component" : "FormInput",
            "props" : {
                "type" : "text",
                "id" : "zip",
                "name" : "zip",
                "defaultValue" : null,
                "placeholder": "Zip Code",
				"autoComplete" : "postal-code",
				"size" : "40",
				"display" : "horizontal",
				"required" : "required",
				"label" : "Zip Code : ",
				"tooltip" : "Please enter your Zip Code",
				"validate" : "isValidUSZipCode"
            }
        },{
            "component" : "FormSelect",
            "props" : {
                "id" : "country",
                "name" : "country",
				"size" : null,
				"defaultValue" : "",
                "placeholder": "Country",
				"autoComplete" : "country",
				"multiple" : null,
				"required" : "required",
				"display" : "horizontal",
				"label" : "Country : ",
				"tooltip" : "Please select your Country",
				"options" : [
					{ "value" : "", "text" : "" , "disabled" : "disabled"},
					{ "text": "United States", "value": "US" },
					{ "text": "Afghanistan", "value": "AF" },
					{ "text": "Albania", "value": "AL" },
					{ "text": "Algeria", "value": "DZ" },
					{ "text": "Andorra", "value": "AD" },
					{ "text": "Angola", "value": "AO" },
					{ "text": "Antigua and Barbuda", "value": "AG" },
					{ "text": "Argentina", "value": "AR" },
					{ "text": "Armenia", "value": "AM" },
					{ "text": "Australia", "value": "AU" },
					{ "text": "Austria", "value": "AT" },
					{ "text": "Azerbaijan", "value": "AZ" },
					{ "text": "Bahamas", "value": "BS" },
					{ "text": "Bahrain", "value": "BH" },
					{ "text": "Bangladesh", "value": "BD" },
					{ "text": "Barbados", "value": "BB" },
					{ "text": "Belarus", "value": "BY" },
					{ "text": "Belgium", "value": "BE" },
					{ "text": "Belize", "value": "BZ" },
					{ "text": "Benin", "value": "BJ" },
					{ "text": "Bhutan", "value": "BT" },
					{ "text": "Bolivia", "value": "BO" },
					{ "text": "Bosnia and Herzegovina", "value": "BA" },
					{ "text": "Botswana", "value": "BW" },
					{ "text": "Brazil", "value": "BR" },
					{ "text": "Brunei", "value": "BN" },
					{ "text": "Bulgaria", "value": "BG" },
					{ "text": "Burkina Faso", "value": "BF" },
					{ "text": "Burundi", "value": "BI" },
					{ "text": "Cabo Verde", "value": "CV" },
					{ "text": "Cambodia", "value": "KH" },
					{ "text": "Cameroon", "value": "CM" },
					{ "text": "Canada", "value": "CA" },
					{ "text": "Central African Republic", "value": "CF" },
					{ "text": "Chad", "value": "TD" },
					{ "text": "Chile", "value": "CL" },
					{ "text": "China", "value": "CN" },
					{ "text": "Colombia", "value": "CO" },
					{ "text": "Comoros", "value": "KM" },
					{ "text": "Congo (Congo-Brazzaville)", "value": "CG" },
					{ "text": "Costa Rica", "value": "CR" },
					{ "text": "Croatia", "value": "HR" },
					{ "text": "Cuba", "value": "CU" },
					{ "text": "Cyprus", "value": "CY" },
					{ "text": "Czechia (Czech Republic)", "value": "CZ" },
					{ "text": "Democratic Republic of the Congo", "value": "CD" },
					{ "text": "Denmark", "value": "DK" },
					{ "text": "Djibouti", "value": "DJ" },
					{ "text": "Dominica", "value": "DM" },
					{ "text": "Dominican Republic", "value": "DO" },
					{ "text": "Ecuador", "value": "EC" },
					{ "text": "Egypt", "value": "EG" },
					{ "text": "El Salvador", "value": "SV" },
					{ "text": "Equatorial Guinea", "value": "GQ" },
					{ "text": "Eritrea", "value": "ER" },
					{ "text": "Estonia", "value": "EE" },
					{ "text": "Eswatini", "value": "SZ" },
					{ "text": "Ethiopia", "value": "ET" },
					{ "text": "Fiji", "value": "FJ" },
					{ "text": "Finland", "value": "FI" },
					{ "text": "France", "value": "FR" },
					{ "text": "Gabon", "value": "GA" },
					{ "text": "Gambia", "value": "GM" },
					{ "text": "Georgia", "value": "GE" },
					{ "text": "Germany", "value": "DE" },
					{ "text": "Ghana", "value": "GH" },
					{ "text": "Greece", "value": "GR" },
					{ "text": "Grenada", "value": "GD" },
					{ "text": "Guatemala", "value": "GT" },
					{ "text": "Guinea", "value": "GN" },
					{ "text": "Guinea-Bissau", "value": "GW" },
					{ "text": "Guyana", "value": "GY" },
					{ "text": "Haiti", "value": "HT" },
					{ "text": "Honduras", "value": "HN" },
					{ "text": "Hungary", "value": "HU" },
					{ "text": "Iceland", "value": "IS" },
					{ "text": "India", "value": "IN" },
					{ "text": "Indonesia", "value": "ID" },
					{ "text": "Iran", "value": "IR" },
					{ "text": "Iraq", "value": "IQ" },
					{ "text": "Ireland", "value": "IE" },
					{ "text": "Israel", "value": "IL" },
					{ "text": "Italy", "value": "IT" },
					{ "text": "Jamaica", "value": "JM" },
					{ "text": "Japan", "value": "JP" },
					{ "text": "Jordan", "value": "JO" },
					{ "text": "Kazakhstan", "value": "KZ" },
					{ "text": "Kenya", "value": "KE" },
					{ "text": "Kiribati", "value": "KI" },
					{ "text": "Kuwait", "value": "KW" },
					{ "text": "Kyrgyzstan", "value": "KG" },
					{ "text": "Laos", "value": "LA" },
					{ "text": "Latvia", "value": "LV" },
					{ "text": "Lebanon", "value": "LB" },
					{ "text": "Lesotho", "value": "LS" },
					{ "text": "Liberia", "value": "LR" },
					{ "text": "Libya", "value": "LY" },
					{ "text": "Liechtenstein", "value": "LI" },
					{ "text": "Lithuania", "value": "LT" },
					{ "text": "Luxembourg", "value": "LU" },
					{ "text": "Madagascar", "value": "MG" },
					{ "text": "Malawi", "value": "MW" },
					{ "text": "Malaysia", "value": "MY" },
					{ "text": "Maldives", "value": "MV" },
					{ "text": "Mali", "value": "ML" },
					{ "text": "Malta", "value": "MT" },
					{ "text": "Marshall Islands", "value": "MH" },
					{ "text": "Mauritania", "value": "MR" },
					{ "text": "Mauritius", "value": "MU" },
					{ "text": "Mexico", "value": "MX" },
					{ "text": "Micronesia", "value": "FM" },
					{ "text": "Moldova", "value": "MD" },
					{ "text": "Monaco", "value": "MC" },
					{ "text": "Mongolia", "value": "MN" },
					{ "text": "Montenegro", "value": "ME" },
					{ "text": "Morocco", "value": "MA" },
					{ "text": "Mozambique", "value": "MZ" },
					{ "text": "Myanmar (Burma)", "value": "MM" },
					{ "text": "Namibia", "value": "NA" },
					{ "text": "Nauru", "value": "NR" },
					{ "text": "Nepal", "value": "NP" },
					{ "text": "Netherlands", "value": "NL" },
					{ "text": "New Zealand", "value": "NZ" },
					{ "text": "Nicaragua", "value": "NI" },
					{ "text": "Niger", "value": "NE" },
					{ "text": "Nigeria", "value": "NG" },
					{ "text": "North Korea", "value": "KP" },
					{ "text": "North Macedonia", "value": "MK" },
					{ "text": "Norway", "value": "NO" },
					{ "text": "Oman", "value": "OM" },
					{ "text": "Pakistan", "value": "PK" },
					{ "text": "Palau", "value": "PW" },
					{ "text": "Palestine State", "value": "PS" },
					{ "text": "Panama", "value": "PA" },
					{ "text": "Papua New Guinea", "value": "PG" },
					{ "text": "Paraguay", "value": "PY" },
					{ "text": "Peru", "value": "PE" },
					{ "text": "Philippines", "value": "PH" },
					{ "text": "Poland", "value": "PL" },
					{ "text": "Portugal", "value": "PT" },
					{ "text": "Qatar", "value": "QA" },
					{ "text": "Romania", "value": "RO" },
					{ "text": "Russia", "value": "RU" },
					{ "text": "Rwanda", "value": "RW" },
					{ "text": "Saint Kitts and Nevis", "value": "KN" },
					{ "text": "Saint Lucia", "value": "LC" },
					{ "text": "Saint Vincent and the Grenadines", "value": "VC" },
					{ "text": "Samoa", "value": "WS" },
					{ "text": "San Marino", "value": "SM" },
					{ "text": "Sao Tome and Principe", "value": "ST" },
					{ "text": "Saudi Arabia", "value": "SA" },
					{ "text": "Senegal", "value": "SN" },
					{ "text": "Serbia", "value": "RS" },
					{ "text": "Seychelles", "value": "SC" },
					{ "text": "Sierra Leone", "value": "SL" },
					{ "text": "Singapore", "value": "SG" },
					{ "text": "Slovakia", "value": "SK" },
					{ "text": "Slovenia", "value": "SI" },
					{ "text": "Solomon Islands", "value": "SB" },
					{ "text": "Somalia", "value": "SO" },
					{ "text": "South Africa", "value": "ZA" },
					{ "text": "South Korea", "value": "KR" },
					{ "text": "South Sudan", "value": "SS" },
					{ "text": "Spain", "value": "ES" },
					{ "text": "Sri Lanka", "value": "LK" },
					{ "text": "Sudan", "value": "SD" },
					{ "text": "Suriname", "value": "SR" },
					{ "text": "Sweden", "value": "SE" },
					{ "text": "Switzerland", "value": "CH" },
					{ "text": "Syria", "value": "SY" },
					{ "text": "Taiwan", "value": "TW" },
					{ "text": "Tajikistan", "value": "TJ" },
					{ "text": "Tanzania", "value": "TZ" },
					{ "text": "Thailand", "value": "TH" },
					{ "text": "Timor-Leste", "value": "TL" },
					{ "text": "Togo", "value": "TG" },
					{ "text": "Tonga", "value": "TO" },
					{ "text": "Trinidad and Tobago", "value": "TT" },
					{ "text": "Tunisia", "value": "TN" },
					{ "text": "Turkey", "value": "TR" },
					{ "text": "Turkmenistan", "value": "TM" },
					{ "text": "Tuvalu", "value": "TV" },
					{ "text": "Uganda", "value": "UG" },
					{ "text": "Ukraine", "value": "UA" },
					{ "text": "United Arab Emirates", "value": "AE" },
					{ "text": "United Kingdom", "value": "GB" },
					{ "text": "Uruguay", "value": "UY" },
					{ "text": "Uzbekistan", "value": "UZ" },
					{ "text": "Vanuatu", "value": "VU" },
					{ "text": "Vatican City", "value": "VA" },
					{ "text": "Venezuela", "value": "VE" },
					{ "text": "Vietnam", "value": "VN" },
					{ "text": "Yemen", "value": "YE" },
					{ "text": "Zambia", "value": "ZM" },
					{ "text": "Zimbabwe", "value": "ZW" }
				]
            }
        },
		{
            "component" : "FormInput",
            "props" : {
                "type" : "tel",
                "id" : "phone",
                "name" : "phone",
                "defaultValue" : null,
                "placeholder": "Phone Number",
				"autoComplete" : "tel",
				"size" : "40",
				"display" : "horizontal",
				"required" : "required",
				"label" : "Phone Number : ",
				"tooltip" : "Please enter your Phone Number",
				"validate" : "isValidUSPhoneNumber"
            }
        },
		{
            "component" : "FormInput",
            "props" : {
                "type" : "email",
                "id" : "email",
                "name" : "email",
                "defaultValue" : null,
                "placeholder": "Email Address",
				"autoComplete" : "email",
				"size" : "40",
				"display" : "horizontal",
				"required" : "required",
				"label" : "Email Address : ",
				"tooltip" : "Please enter your Email Address",
				"validate" : "isValidEmailAddress"
            }
        },
		{
            "component" : "FormRadio",
            "props" : {
                "id" : "shippingMethod",
                "name" : "shippingMethod",
				"label" : "Shipping Method : ",
				"display" : "vertical",
				"required" : "required",
				"validate" : "isOneRadioSelected",
				"tooltip" : "Please select your Shipping Method",
				"options" : [
					{ "value" : "USPS-GA", "text" : "USPS Ground Advantage ( 2 - 5 days ) $9.99", "checked" : "" },
					{ "value" : "USPS-PM", "text" : "USPS Priority Mail ( 2 - 3 days ) $14.99", "checked" : "" },
					{ "value" : "USPS-PMX", "text" : "USPS Priority Mail Express ( 1 - 3 days ) $39.99", "checked" : "" },
					{ "value" : "USPS-FCP-I", "text" : "USPS First Class Package International ( Varies ) $24.99", "checked" : "" },
					{ "value" : "USPS-PM-I", "text" : "USPS Priority Mail International ( 6 - 10 days ) $39.99", "checked" : "" },
					{ "value" : "USPS-PMX-I", "text" : "USPS Priority Mail Express International ( 3 - 5 days ) $69.99", "checked" : "" }
				]
            }
        },
		{
            "component" : "FormButton",
            "props" : {
				"type" : "submit",
                "id" : "submit",
                "text" : "Checkout"
            }
        }
    ]
}